QPanda3D/Panda3DWorld.py
QPanda3D/QMouseWatcherNode.py
QPanda3D/QPanda3DWidget.py
QPanda3D/QPanda3D_Buttons_Translation.py
QPanda3D/QPanda3D_Keys_Translation.py
QPanda3D/QPanda3D_Modifiers_Translation.py
QPanda3D/__init__.py
QPanda3D/Helpers/Env_Grid_Maker.py
QPanda3D/Helpers/__init__.py
QPanda3D/Tools/__init__.py
QPanda3D/Tools/generate_qt_to_pd3d_translator.py
QPanda3D-0.2.10.dist-info/LICENSE
QPanda3D-0.2.10.dist-info/METADATA
QPanda3D-0.2.10.dist-info/WHEEL
QPanda3D-0.2.10.dist-info/top_level.txt
QPanda3D-0.2.10.dist-info/RECORD
