Metadata-Version: 2.1
Name: QPanda3D
Version: 0.2.10
Summary: A binding to use Panda3D as a PyQt5 widget
Home-page: https://github.com/ParisNeo/QPanda3D
Author: Saifeddine ALOUI
Author-email: aloui.saifeddine@gmail.com
License: UNKNOWN
Platform: UNKNOWN
Classifier: Programming Language :: Python :: 3
Classifier: License :: OSI Approved :: GNU General Public License v3 (GPLv3)
Classifier: Operating System :: OS Independent
Requires-Dist: Panda3D (>=1.10.3)
Requires-Dist: PyQt5
Provides-Extra: dev
